{
  "change": "author-emulation-e2e-scaffold",
  "triage": "L",
  "phase": "plan-complete",
  "spec_status": "signed",
  "design": "complete rev 2+3 (design.md + obs #944; architecture_impact additive, 0 deviations; ADRs 0047-0049 draft; 39/39 REQs; M-09 R-G ruling LANDED — contentDigest normalization, pre-apply gate CLEARED)",
  "steward_foresight": "ALIGNED (obs #945; CQ-1/2/3 owner-affirmed 2026-07-13)",
  "slices": true,
  "slice_ids": ["S-000", "S-001", "S-002", "S-003", "S-004"],
  "slices_rev": 3,
  "plan_verify": "READY (owner-ruled at iteration 3, 2026-07-13; trajectory 17→5→6; Judge A clean 2x; residue = 5 pointer-gaps resolve-at-apply + M-09 design ruling pre-apply gate for S-003)",
  "plan_complete": true,
  "build_gate": "SATISFIED (schematic-local-files merged+archived, main @ 4af1272 merged into branch db620ff)",
  "verify_final": "pending",
  "arch_audit": "pending",
  "completed_phases": ["triage", "explore", "propose"],
  "updated_at": "2026-07-13"
}
